flaxdiff/__init__.py
flaxdiff/utils.py
flaxdiff/data/__init__.py
flaxdiff/data/benchmark_decord.py
flaxdiff/data/dataloaders.py
flaxdiff/data/dataset_map.py
flaxdiff/data/online_loader.py
flaxdiff/data/sources/audio_utils.py
flaxdiff/data/sources/av_example.py
flaxdiff/data/sources/av_utils.py
flaxdiff/data/sources/base.py
flaxdiff/data/sources/images.py
flaxdiff/data/sources/utils.py
flaxdiff/data/sources/videos.py
flaxdiff/data/sources/voxceleb2.py
flaxdiff/inference/__init__.py
flaxdiff/inference/pipeline.py
flaxdiff/inference/utils.py
flaxdiff/inputs/__init__.py
flaxdiff/inputs/encoders.py
flaxdiff/metrics/__init__.py
flaxdiff/metrics/common.py
flaxdiff/metrics/images.py
flaxdiff/metrics/inception.py
flaxdiff/metrics/psnr.py
flaxdiff/metrics/ssim.py
flaxdiff/metrics/utils.py
flaxdiff/models/__init__.py
flaxdiff/models/attention.py
flaxdiff/models/common.py
flaxdiff/models/favor_fastattn.py
flaxdiff/models/general.py
flaxdiff/models/hilbert.py
flaxdiff/models/simple_dit.py
flaxdiff/models/simple_mmdit.py
flaxdiff/models/simple_unet.py
flaxdiff/models/simple_vit.py
flaxdiff/models/unet_3d.py
flaxdiff/models/unet_3d_blocks.py
flaxdiff/models/vit_common.py
flaxdiff/models/autoencoder/__init__.py
flaxdiff/models/autoencoder/autoencoder.py
flaxdiff/models/autoencoder/diffusers.py
flaxdiff/models/autoencoder/simple_autoenc.py
flaxdiff/predictors/__init__.py
flaxdiff/samplers/__init__.py
flaxdiff/samplers/common.py
flaxdiff/samplers/ddim.py
flaxdiff/samplers/ddpm.py
flaxdiff/samplers/euler.py
flaxdiff/samplers/heun_sampler.py
flaxdiff/samplers/multistep_dpm.py
flaxdiff/samplers/rk4_sampler.py
flaxdiff/schedulers/__init__.py
flaxdiff/schedulers/common.py
flaxdiff/schedulers/continuous.py
flaxdiff/schedulers/cosine.py
flaxdiff/schedulers/discrete.py
flaxdiff/schedulers/exp.py
flaxdiff/schedulers/karras.py
flaxdiff/schedulers/linear.py
flaxdiff/schedulers/sqrt.py
flaxdiff/trainer/__init__.py
flaxdiff/trainer/autoencoder_trainer.py
flaxdiff/trainer/diffusion_trainer.py
flaxdiff-0.2.9.dist-info/METADATA
flaxdiff-0.2.9.dist-info/WHEEL
flaxdiff-0.2.9.dist-info/top_level.txt
flaxdiff-0.2.9.dist-info/RECORD
