Metadata-Version: 2.4
Name: flaxdiff
Version: 0.2.9
Summary: A versatile and easy to understand Diffusion library
Author-email: Ashish Kumar Singh <ashishkmr472@gmail.com>
License-Expression: MIT
Requires-Dist: flax>=0.8.4
Requires-Dist: jax>=0.4.28
Requires-Dist: optax>=0.2.2
Requires-Dist: orbax
Requires-Dist: numpy
Requires-Dist: clu
Requires-Dist: einops
Requires-Dist: tqdm
Requires-Dist: grain
Requires-Dist: termcolor
Requires-Dist: augmax
Requires-Dist: albumentations
Requires-Dist: rich
Requires-Dist: python-dotenv
